MANIFEST.in
README.txt
setup.cfg
setup.py
Paste-1.7.5.1-py2.4.egg/EGG-INFO/SOURCES.txt
Paste-1.7.5.1-py2.4.egg/EGG-INFO/dependency_links.txt
Paste-1.7.5.1-py2.4.egg/EGG-INFO/entry_points.txt
Paste-1.7.5.1-py2.4.egg/EGG-INFO/namespace_packages.txt
Paste-1.7.5.1-py2.4.egg/EGG-INFO/requires.txt
Paste-1.7.5.1-py2.4.egg/EGG-INFO/top_level.txt
PasteDeploy-1.3.4-py2.4.egg/EGG-INFO/SOURCES.txt
PasteDeploy-1.3.4-py2.4.egg/EGG-INFO/dependency_links.txt
PasteDeploy-1.3.4-py2.4.egg/EGG-INFO/entry_points.txt
PasteDeploy-1.3.4-py2.4.egg/EGG-INFO/namespace_packages.txt
PasteDeploy-1.3.4-py2.4.egg/EGG-INFO/requires.txt
PasteDeploy-1.3.4-py2.4.egg/EGG-INFO/top_level.txt
PasteScript-1.7.3-py2.4.egg/EGG-INFO/SOURCES.txt
PasteScript-1.7.3-py2.4.egg/EGG-INFO/dependency_links.txt
PasteScript-1.7.3-py2.4.egg/EGG-INFO/entry_points.txt
PasteScript-1.7.3-py2.4.egg/EGG-INFO/namespace_packages.txt
PasteScript-1.7.3-py2.4.egg/EGG-INFO/requires.txt
PasteScript-1.7.3-py2.4.egg/EGG-INFO/top_level.txt
collective/__init__.py
collective.patchlinguaploneissue273.egg-info/PKG-INFO
collective.patchlinguaploneissue273.egg-info/SOURCES.txt
collective.patchlinguaploneissue273.egg-info/dependency_links.txt
collective.patchlinguaploneissue273.egg-info/entry_points.txt
collective.patchlinguaploneissue273.egg-info/namespace_packages.txt
collective.patchlinguaploneissue273.egg-info/not-zip-safe
collective.patchlinguaploneissue273.egg-info/paster_plugins.txt
collective.patchlinguaploneissue273.egg-info/requires.txt
collective.patchlinguaploneissue273.egg-info/top_level.txt
collective/patchlinguaploneissue273/README.txt
collective/patchlinguaploneissue273/__init__.py
collective/patchlinguaploneissue273/configure.zcml
collective/patchlinguaploneissue273/patch.py
collective/patchlinguaploneissue273/tests.py
docs/HISTORY.txt
docs/INSTALL.txt
docs/LICENSE.txt