Metadata-Version: 1.0
Name: collective.patchlinguaploneissue273
Version: 1.0
Summary: Try to fix http://plone.org/products/linguaplone/issues/273
Home-page: http://svn.plone.org/svn/collective/
Author: yboussard
Author-email: youenn.boussard@alterway.fr
License: GPL
Platform: UNKNOWN
Classifier: Framework :: Plone
Classifier: Programming Language :: Python
